{
  "torah": {
    "passage": "Numbers 16:14 - 16:19",
    "versions": {
      "leb": [
        {
          "chapter": 16,
          "verse": 14,
          "text": "Surely, you have not brought us to a land that flows with milk and honey, and you have not given us the inheritance of fields and a vineyard. Will you gouge out the eyes of these men? We will not come!”",
          "isHeading": false,
          "interlinear": {
            "tokens": [
              {
                "text": "#19=L",
                "wordIndex": 0
              },
              {
                "text": "נַעֲלֶֽה\\׃",
                "wordIndex": 1
              },
              {
                "text": "na.'a.Leh",
                "wordIndex": 2
              },
              {
                "text": "we",
                "wordIndex": 3
              },
              {
                "text": "will",
                "wordIndex": 4
              },
              {
                "text": "come",
                "wordIndex": 5
              },
              {
                "text": "up",
                "wordIndex": 6
              },
              {
                "text": "{H5927G}\\H9016",
                "wordIndex": 7,
                "lex": {
                  "code": "H5927",
                  "lemma": "עָלָה",
                  "translit": "a.lah",
                  "morph": "H:V",
                  "gloss": "to ascend: regurgitate : regurgitate/chew(cud)<br>1) to go up, ascend, climb<br>1a) (Qal)<br>1a1) to go up, ascend<br>1a2) to meet, visit, follow, depart, withdraw, retreat<br>1a3) to go up, come up (of animals)<br>1a4) to spring up, grow, shoot forth (of vegetation)<br>1a5) to go up, go up over, rise (of natural phenomenon)<br>1a6) to come up (before God)<br>1a7) to go up, go up over, extend (of boundary)<br>1a8) to excel, be superior to<br>1b) (Niphal)<br>1b1) to be taken up, be brought up, be taken away<br>1b2) to take oneself away<br>1b3) to be exalted<br>1c) (Hiphil)<br>1c1) to bring up, cause to ascend or climb, cause to go up<br>1c2) to bring up, bring against, take away<br>1c3) to bring up, draw up, train<br>1c4) to cause to ascend<br>1c5) to rouse, stir up (mentally)<br>1c6) to offer, bring up (of gifts)<br>1c7) to exalt<br>1c8) to cause to ascend, offer<br>1d) (Hophal)<br>1d1) to be carried away, be led up<br>1d2) to be taken up into, be inserted in<br>1d3) to be offered<br>1e) (Hithpael) to lift oneself",
                  "raw": "H5927\tH5927M = a Meaning of\tH5927G\tעָלָה\ta.lah\tH:V\tto ascend: regurgitate\t: regurgitate/chew(cud)<br>1) to go up, ascend, climb<br>1a) (Qal)<br>1a1) to go up, ascend<br>1a2) to meet, visit, follow, depart, withdraw, retreat<br>1a3) to go up, come up (of animals)<br>1a4) to spring up, grow, shoot forth (of vegetation)<br>1a5) to go up, go up over, rise (of natural phenomenon)<br>1a6) to come up (before God)<br>1a7) to go up, go up over, extend (of boundary)<br>1a8) to excel, be superior to<br>1b) (Niphal)<br>1b1) to be taken up, be brought up, be taken away<br>1b2) to take oneself away<br>1b3) to be exalted<br>1c) (Hiphil)<br>1c1) to bring up, cause to ascend or climb, cause to go up<br>1c2) to bring up, bring against, take away<br>1c3) to bring up, draw up, train<br>1c4) to cause to ascend<br>1c5) to rouse, stir up (mentally)<br>1c6) to offer, bring up (of gifts)<br>1c7) to exalt<br>1c8) to cause to ascend, offer<br>1d) (Hophal)<br>1d1) to be carried away, be led up<br>1d2) to be taken up into, be inserted in<br>1d3) to be offered<br>1e) (Hithpael) to lift oneself"
                }
              },
              {
                "text": "HVqi1cp",
                "wordIndex": 8
              },
              {
                "text": "H5927G",
                "wordIndex": 9,
                "lex": {
                  "code": "H5927",
                  "lemma": "עָלָה",
                  "translit": "a.lah",
                  "morph": "H:V",
                  "gloss": "to ascend: regurgitate : regurgitate/chew(cud)<br>1) to go up, ascend, climb<br>1a) (Qal)<br>1a1) to go up, ascend<br>1a2) to meet, visit, follow, depart, withdraw, retreat<br>1a3) to go up, come up (of animals)<br>1a4) to spring up, grow, shoot forth (of vegetation)<br>1a5) to go up, go up over, rise (of natural phenomenon)<br>1a6) to come up (before God)<br>1a7) to go up, go up over, extend (of boundary)<br>1a8) to excel, be superior to<br>1b) (Niphal)<br>1b1) to be taken up, be brought up, be taken away<br>1b2) to take oneself away<br>1b3) to be exalted<br>1c) (Hiphil)<br>1c1) to bring up, cause to ascend or climb, cause to go up<br>1c2) to bring up, bring against, take away<br>1c3) to bring up, draw up, train<br>1c4) to cause to ascend<br>1c5) to rouse, stir up (mentally)<br>1c6) to offer, bring up (of gifts)<br>1c7) to exalt<br>1c8) to cause to ascend, offer<br>1d) (Hophal)<br>1d1) to be carried away, be led up<br>1d2) to be taken up into, be inserted in<br>1d3) to be offered<br>1e) (Hithpael) to lift oneself",
                  "raw": "H5927\tH5927M = a Meaning of\tH5927G\tעָלָה\ta.lah\tH:V\tto ascend: regurgitate\t: regurgitate/chew(cud)<br>1) to go up, ascend, climb<br>1a) (Qal)<br>1a1) to go up, ascend<br>1a2) to meet, visit, follow, depart, withdraw, retreat<br>1a3) to go up, come up (of animals)<br>1a4) to spring up, grow, shoot forth (of vegetation)<br>1a5) to go up, go up over, rise (of natural phenomenon)<br>1a6) to come up (before God)<br>1a7) to go up, go up over, extend (of boundary)<br>1a8) to excel, be superior to<br>1b) (Niphal)<br>1b1) to be taken up, be brought up, be taken away<br>1b2) to take oneself away<br>1b3) to be exalted<br>1c) (Hiphil)<br>1c1) to bring up, cause to ascend or climb, cause to go up<br>1c2) to bring up, bring against, take away<br>1c3) to bring up, draw up, train<br>1c4) to cause to ascend<br>1c5) to rouse, stir up (mentally)<br>1c6) to offer, bring up (of gifts)<br>1c7) to exalt<br>1c8) to cause to ascend, offer<br>1d) (Hophal)<br>1d1) to be carried away, be led up<br>1d2) to be taken up into, be inserted in<br>1d3) to be offered<br>1e) (Hithpael) to lift oneself"
                }
              },
              {
                "text": "{H5927G=עָלָה=:",
                "wordIndex": 10,
                "lex": {
                  "code": "H5927",
                  "lemma": "עָלָה",
                  "translit": "a.lah",
                  "morph": "H:V",
                  "gloss": "to ascend: regurgitate : regurgitate/chew(cud)<br>1) to go up, ascend, climb<br>1a) (Qal)<br>1a1) to go up, ascend<br>1a2) to meet, visit, follow, depart, withdraw, retreat<br>1a3) to go up, come up (of animals)<br>1a4) to spring up, grow, shoot forth (of vegetation)<br>1a5) to go up, go up over, rise (of natural phenomenon)<br>1a6) to come up (before God)<br>1a7) to go up, go up over, extend (of boundary)<br>1a8) to excel, be superior to<br>1b) (Niphal)<br>1b1) to be taken up, be brought up, be taken away<br>1b2) to take oneself away<br>1b3) to be exalted<br>1c) (Hiphil)<br>1c1) to bring up, cause to ascend or climb, cause to go up<br>1c2) to bring up, bring against, take away<br>1c3) to bring up, draw up, train<br>1c4) to cause to ascend<br>1c5) to rouse, stir up (mentally)<br>1c6) to offer, bring up (of gifts)<br>1c7) to exalt<br>1c8) to cause to ascend, offer<br>1d) (Hophal)<br>1d1) to be carried away, be led up<br>1d2) to be taken up into, be inserted in<br>1d3) to be offered<br>1e) (Hithpael) to lift oneself",
                  "raw": "H5927\tH5927M = a Meaning of\tH5927G\tעָלָה\ta.lah\tH:V\tto ascend: regurgitate\t: regurgitate/chew(cud)<br>1) to go up, ascend, climb<br>1a) (Qal)<br>1a1) to go up, ascend<br>1a2) to meet, visit, follow, depart, withdraw, retreat<br>1a3) to go up, come up (of animals)<br>1a4) to spring up, grow, shoot forth (of vegetation)<br>1a5) to go up, go up over, rise (of natural phenomenon)<br>1a6) to come up (before God)<br>1a7) to go up, go up over, extend (of boundary)<br>1a8) to excel, be superior to<br>1b) (Niphal)<br>1b1) to be taken up, be brought up, be taken away<br>1b2) to take oneself away<br>1b3) to be exalted<br>1c) (Hiphil)<br>1c1) to bring up, cause to ascend or climb, cause to go up<br>1c2) to bring up, bring against, take away<br>1c3) to bring up, draw up, train<br>1c4) to cause to ascend<br>1c5) to rouse, stir up (mentally)<br>1c6) to offer, bring up (of gifts)<br>1c7) to exalt<br>1c8) to cause to ascend, offer<br>1d) (Hophal)<br>1d1) to be carried away, be led up<br>1d2) to be taken up into, be inserted in<br>1d3) to be offered<br>1e) (Hithpael) to lift oneself"
                }
              },
              {
                "text": "rise»to",
                "wordIndex": 11
              },
              {
                "text": "ascend:1_rise;_go}\\H9016=׃=verseEnd",
                "wordIndex": 12,
                "lex": {
                  "code": "H9016",
                  "lemma": ":",
                  "translit": ":",
                  "morph": "Punct.",
                  "gloss": "[.] Punctuation Sof-Pasuq: ends a verse",
                  "raw": "H9016\tH9016 =\tH9016\t:\t:\tPunct.\t[.]\tPunctuation Sof-Pasuq: ends a verse"
                }
              }
            ],
            "originalVerseText": "#19=L נַעֲלֶֽה\\׃ na.'a.Leh we will come up {H5927G}\\H9016 HVqi1cp H5927G {H5927G=עָלָה=: rise»to ascend:1_rise;_go}\\H9016=׃=verseEnd"
          }
        },
        {
          "chapter": 16,
          "verse": 15,
          "text": "Then Moses became angry, and he said to Yahweh, “Do not notice their grain offering. I have not offered one donkey from them, and I have not mistreated one of them.”",
          "isHeading": false,
          "interlinear": {
            "tokens": [
              {
                "text": "#20=L",
                "wordIndex": 0
              },
              {
                "text": "מֵ/הֶֽם\\׃",
                "wordIndex": 1
              },
              {
                "text": "me./Hem",
                "wordIndex": 2
              },
              {
                "text": "of",
                "wordIndex": 3
              },
              {
                "text": "<the>/",
                "wordIndex": 4
              },
              {
                "text": "them",
                "wordIndex": 5
              },
              {
                "text": "H9006/{H9038}\\H9016",
                "wordIndex": 6,
                "lex": {
                  "code": "H9006",
                  "lemma": "/מ",
                  "translit": "m",
                  "morph": "Prefix",
                  "gloss": "from Prefix mem: from",
                  "raw": "H9006\tH9006 =\tH9006\t/מ\tm\tPrefix\tfrom\tPrefix mem: from"
                }
              },
              {
                "text": "HRd/Sp3mp",
                "wordIndex": 7
              },
              {
                "text": "H9038_B",
                "wordIndex": 8,
                "lex": {
                  "code": "H9038",
                  "lemma": "הֶם",
                  "translit": "hem",
                  "morph": "Op3m",
                  "gloss": "them Personal object pronoun -  suffix for propositions and verbs without an object: 3rd person masculine plural",
                  "raw": "H9038\tH9038 =\tH9038\tהֶם\them\tOp3m\tthem\tPersonal object pronoun -  suffix for propositions and verbs without an object: 3rd person masculine plural"
                }
              },
              {
                "text": "H9006=מ=from/{H9038=Op3m=them}\\H9016=׃=verseEnd",
                "wordIndex": 9,
                "lex": {
                  "code": "H9006",
                  "lemma": "/מ",
                  "translit": "m",
                  "morph": "Prefix",
                  "gloss": "from Prefix mem: from",
                  "raw": "H9006\tH9006 =\tH9006\t/מ\tm\tPrefix\tfrom\tPrefix mem: from"
                }
              }
            ],
            "originalVerseText": "#20=L מֵ/הֶֽם\\׃ me./Hem of <the>/ them H9006/{H9038}\\H9016 HRd/Sp3mp H9038_B H9006=מ=from/{H9038=Op3m=them}\\H9016=׃=verseEnd"
          }
        },
        {
          "chapter": 16,
          "verse": 16,
          "text": "And Moses said to Korah, “You and your entire company will be before Yahweh tomorrow, you and they and Aaron.",
          "isHeading": false,
          "interlinear": {
            "tokens": [
              {
                "text": "#14=L",
                "wordIndex": 0
              },
              {
                "text": "מָחָֽר\\׃",
                "wordIndex": 1
              },
              {
                "text": "ma.Char",
                "wordIndex": 2
              },
              {
                "text": "tomorrow",
                "wordIndex": 3
              },
              {
                "text": "{H4279}\\H9016",
                "wordIndex": 4,
                "lex": {
                  "code": "H4279",
                  "lemma": "מָחָר",
                  "translit": "ma.char",
                  "morph": "H:N-M",
                  "gloss": "tomorrow 1) tomorrow, in time to come, in the future<br>1a) tomorrow (as the day following the present day)<br>1b) in future time",
                  "raw": "H4279\tH4279 =\tH4279\tמָחָר\tma.char\tH:N-M\ttomorrow\t1) tomorrow, in time to come, in the future<br>1a) tomorrow (as the day following the present day)<br>1b) in future time"
                }
              },
              {
                "text": "HNcmsa",
                "wordIndex": 5
              },
              {
                "text": "H4279",
                "wordIndex": 6,
                "lex": {
                  "code": "H4279",
                  "lemma": "מָחָר",
                  "translit": "ma.char",
                  "morph": "H:N-M",
                  "gloss": "tomorrow 1) tomorrow, in time to come, in the future<br>1a) tomorrow (as the day following the present day)<br>1b) in future time",
                  "raw": "H4279\tH4279 =\tH4279\tמָחָר\tma.char\tH:N-M\ttomorrow\t1) tomorrow, in time to come, in the future<br>1a) tomorrow (as the day following the present day)<br>1b) in future time"
                }
              },
              {
                "text": "{H4279=מָחָר=tomorrow}\\H9016=׃=verseEnd",
                "wordIndex": 7,
                "lex": {
                  "code": "H4279",
                  "lemma": "מָחָר",
                  "translit": "ma.char",
                  "morph": "H:N-M",
                  "gloss": "tomorrow 1) tomorrow, in time to come, in the future<br>1a) tomorrow (as the day following the present day)<br>1b) in future time",
                  "raw": "H4279\tH4279 =\tH4279\tמָחָר\tma.char\tH:N-M\ttomorrow\t1) tomorrow, in time to come, in the future<br>1a) tomorrow (as the day following the present day)<br>1b) in future time"
                }
              }
            ],
            "originalVerseText": "#14=L מָחָֽר\\׃ ma.Char tomorrow {H4279}\\H9016 HNcmsa H4279 {H4279=מָחָר=tomorrow}\\H9016=׃=verseEnd"
          }
        },
        {
          "chapter": 16,
          "verse": 17,
          "text": "Each one take his censer, and put incense on it and you will present it before Yahweh, and each of you bring his censer, two hundred and fifty censers, you and Aaron, each his censer.”",
          "isHeading": false,
          "interlinear": {
            "tokens": [
              {
                "text": "#18=L",
                "wordIndex": 0
              },
              {
                "text": "מַחְתָּתֽ/וֹ\\׃",
                "wordIndex": 1
              },
              {
                "text": "mach.ta.T/o",
                "wordIndex": 2
              },
              {
                "text": "censer/",
                "wordIndex": 3
              },
              {
                "text": "his",
                "wordIndex": 4
              },
              {
                "text": "{H4289}/H9023\\H9016",
                "wordIndex": 5,
                "lex": {
                  "code": "H4289",
                  "lemma": "מַחְתָּה",
                  "translit": "mach.tah",
                  "morph": "H:N-F",
                  "gloss": "censer 1) fire-holder, censer, firepan, snuff dish, tray<br>1a) snuff-dish<br>1b) fire-pans<br>1c) censer",
                  "raw": "H4289\tH4289 =\tH4289\tמַחְתָּה\tmach.tah\tH:N-F\tcenser\t1) fire-holder, censer, firepan, snuff dish, tray<br>1a) snuff-dish<br>1b) fire-pans<br>1c) censer"
                }
              },
              {
                "text": "HNcfsc/Sp3ms",
                "wordIndex": 6
              },
              {
                "text": "H4289_D",
                "wordIndex": 7,
                "lex": {
                  "code": "H4289",
                  "lemma": "מַחְתָּה",
                  "translit": "mach.tah",
                  "morph": "H:N-F",
                  "gloss": "censer 1) fire-holder, censer, firepan, snuff dish, tray<br>1a) snuff-dish<br>1b) fire-pans<br>1c) censer",
                  "raw": "H4289\tH4289 =\tH4289\tמַחְתָּה\tmach.tah\tH:N-F\tcenser\t1) fire-holder, censer, firepan, snuff dish, tray<br>1a) snuff-dish<br>1b) fire-pans<br>1c) censer"
                }
              },
              {
                "text": "{H4289=מַחְתָּה=censer}/H9023=Ps3m=his\\H9016=׃=verseEnd",
                "wordIndex": 8,
                "lex": {
                  "code": "H4289",
                  "lemma": "מַחְתָּה",
                  "translit": "mach.tah",
                  "morph": "H:N-F",
                  "gloss": "censer 1) fire-holder, censer, firepan, snuff dish, tray<br>1a) snuff-dish<br>1b) fire-pans<br>1c) censer",
                  "raw": "H4289\tH4289 =\tH4289\tמַחְתָּה\tmach.tah\tH:N-F\tcenser\t1) fire-holder, censer, firepan, snuff dish, tray<br>1a) snuff-dish<br>1b) fire-pans<br>1c) censer"
                }
              }
            ],
            "originalVerseText": "#18=L מַחְתָּתֽ/וֹ\\׃ mach.ta.T/o censer/ his {H4289}/H9023\\H9016 HNcfsc/Sp3ms H4289_D {H4289=מַחְתָּה=censer}/H9023=Ps3m=his\\H9016=׃=verseEnd"
          }
        },
        {
          "chapter": 16,
          "verse": 18,
          "text": "So each of them took his censer, and they put fire on them, and they placed incense on them; they stood at the doorway of the tent of the assembly of Moses and Aaron.",
          "isHeading": false,
          "interlinear": {
            "tokens": [
              {
                "text": "#15=L",
                "wordIndex": 0
              },
              {
                "text": "וְ/אַהֲרֹֽן\\׃",
                "wordIndex": 1
              },
              {
                "text": "ve./'a.ha.Ron",
                "wordIndex": 2
              },
              {
                "text": "and/",
                "wordIndex": 3
              },
              {
                "text": "Aaron",
                "wordIndex": 4
              },
              {
                "text": "H9002/{H0175}\\H9016",
                "wordIndex": 5,
                "lex": {
                  "code": "H9002",
                  "lemma": "/וְ",
                  "translit": "v",
                  "morph": "H:Conj",
                  "gloss": "and Conjunctive vav -  i.e. followed by prefix, suffix or non-verb (conjunctive) (‘and/but’)",
                  "raw": "H9002\tH9002 =\tH9002\t/וְ\tv\tH:Conj\tand\tConjunctive vav -  i.e. followed by prefix, suffix or non-verb (conjunctive) (‘and/but’)"
                }
              },
              {
                "text": "HC/Npm",
                "wordIndex": 6
              },
              {
                "text": "H0175",
                "wordIndex": 7,
                "lex": {
                  "code": "H0175",
                  "lemma": "אַהֲרֹן",
                  "translit": "a.ha.ron",
                  "morph": "N:N-M-P",
                  "gloss": "Aaron A man of the tribe of Levi living at the time of Egypt and Wilderness, first mentioned at Exo.4.14; <br> son of: Amram (H6019) and Jochebed (H3115); <br> brother of: Moses (H4872) and Miriam (H4813); married to Elisheba (H0472); <br> father of: Nadab (H5070), Abihu (H0030), Eleazar (H0499) and Ithamar (H0385)<BR>Also named: <i>Aarōn</i> (Ἀαρών \"Aaron\" G0002) <BR> § Aaron = \"light bringer\"<br> brother of Moses, a Levite and the first high priest<br>",
                  "raw": "H0175\tH0175 =\tH0175\tאַהֲרֹן\ta.ha.ron\tN:N-M-P\tAaron\tA man of the tribe of Levi living at the time of Egypt and Wilderness, first mentioned at Exo.4.14; <br> son of: Amram (H6019) and Jochebed (H3115); <br> brother of: Moses (H4872) and Miriam (H4813); married to Elisheba (H0472); <br> father of: Nadab (H5070), Abihu (H0030), Eleazar (H0499) and Ithamar (H0385)<BR>Also named: <i>Aarōn</i> (Ἀαρών \"Aaron\" G0002) <BR> § Aaron = \"light bringer\"<br> brother of Moses, a Levite and the first high priest<br>"
                }
              },
              {
                "text": "H9002=ו=and/{H0175=אַהֲרֹן=Aaron»Aaron@Exo.4.14-Heb}\\H9016=׃=verseEnd",
                "wordIndex": 8,
                "lex": {
                  "code": "H9002",
                  "lemma": "/וְ",
                  "translit": "v",
                  "morph": "H:Conj",
                  "gloss": "and Conjunctive vav -  i.e. followed by prefix, suffix or non-verb (conjunctive) (‘and/but’)",
                  "raw": "H9002\tH9002 =\tH9002\t/וְ\tv\tH:Conj\tand\tConjunctive vav -  i.e. followed by prefix, suffix or non-verb (conjunctive) (‘and/but’)"
                }
              }
            ],
            "originalVerseText": "#15=L וְ/אַהֲרֹֽן\\׃ ve./'a.ha.Ron and/ Aaron H9002/{H0175}\\H9016 HC/Npm H0175 H9002=ו=and/{H0175=אַהֲרֹן=Aaron»Aaron@Exo.4.14-Heb}\\H9016=׃=verseEnd"
          }
        },
        {
          "chapter": 16,
          "verse": 19,
          "text": "And Korah summoned them, the entire community, by the doorway of the tent of assembly, and the glory of Yahweh appeared to all the community.",
          "isHeading": false,
          "interlinear": {
            "tokens": [
              {
                "text": "#16=L",
                "wordIndex": 0
              },
              {
                "text": "הָ/עֵדָֽה\\׃\\",
                "wordIndex": 1
              },
              {
                "text": "\\פ",
                "wordIndex": 2
              },
              {
                "text": "ha./'e.Dah",
                "wordIndex": 3
              },
              {
                "text": "the/",
                "wordIndex": 4
              },
              {
                "text": "congregation",
                "wordIndex": 5
              },
              {
                "text": "H9009/{H5712}\\H9016\\",
                "wordIndex": 6,
                "lex": {
                  "code": "H9009",
                  "lemma": "/ה",
                  "translit": "ha",
                  "morph": "Prefix",
                  "gloss": "[the] Prefix hé article: \"the\" for a subject, not object",
                  "raw": "H9009\tH9009 =\tH9009\t/ה\tha\tPrefix\t[the]\tPrefix hé article: \"the\" for a subject, not object"
                }
              },
              {
                "text": "\\H9017",
                "wordIndex": 7,
                "lex": {
                  "code": "H9017",
                  "lemma": "פ",
                  "translit": "P",
                  "morph": "Punct.",
                  "gloss": "[¶] Punctuation Pe paragraph: ends a literary section",
                  "raw": "H9017\tH9017 =\tH9017\tפ\tP\tPunct.\t[¶]\tPunctuation Pe paragraph: ends a literary section"
                }
              },
              {
                "text": "HTd/Ncfsa",
                "wordIndex": 8
              },
              {
                "text": "H5712_B",
                "wordIndex": 9,
                "lex": {
                  "code": "H5712",
                  "lemma": "עֵדָה",
                  "translit": "e.dah",
                  "morph": "H:N-F",
                  "gloss": "congregation congregation, gathering",
                  "raw": "H5712\tH5712 =\tH5712\tעֵדָה\te.dah\tH:N-F\tcongregation\tcongregation, gathering"
                }
              },
              {
                "text": "H9009=ה=the/{H5712=עֵדָה=congregation}\\H9016=׃=verseEnd\\",
                "wordIndex": 10,
                "lex": {
                  "code": "H9009",
                  "lemma": "/ה",
                  "translit": "ha",
                  "morph": "Prefix",
                  "gloss": "[the] Prefix hé article: \"the\" for a subject, not object",
                  "raw": "H9009\tH9009 =\tH9009\t/ה\tha\tPrefix\t[the]\tPrefix hé article: \"the\" for a subject, not object"
                }
              },
              {
                "text": "\\H9017=פ=para",
                "wordIndex": 11,
                "lex": {
                  "code": "H9017",
                  "lemma": "פ",
                  "translit": "P",
                  "morph": "Punct.",
                  "gloss": "[¶] Punctuation Pe paragraph: ends a literary section",
                  "raw": "H9017\tH9017 =\tH9017\tפ\tP\tPunct.\t[¶]\tPunctuation Pe paragraph: ends a literary section"
                }
              }
            ],
            "originalVerseText": "#16=L הָ/עֵדָֽה\\׃\\ \\פ ha./'e.Dah the/ congregation H9009/{H5712}\\H9016\\ \\H9017 HTd/Ncfsa H5712_B H9009=ה=the/{H5712=עֵדָה=congregation}\\H9016=׃=verseEnd\\ \\H9017=פ=para"
          }
        }
      ],
      "nirv": [
        {
          "chapter": 16,
          "verse": 14,
          "text": "“Besides, you haven’t brought us into a land that has plenty of milk and honey. You haven’t given us fields and vineyards of our own. Are you going to poke out the eyes of these men? No! We won’t come!”",
          "isHeading": false,
          "interlinear": {
            "tokens": [
              {
                "text": "#19=L",
                "wordIndex": 0
              },
              {
                "text": "נַעֲלֶֽה\\׃",
                "wordIndex": 1
              },
              {
                "text": "na.'a.Leh",
                "wordIndex": 2
              },
              {
                "text": "we",
                "wordIndex": 3
              },
              {
                "text": "will",
                "wordIndex": 4
              },
              {
                "text": "come",
                "wordIndex": 5
              },
              {
                "text": "up",
                "wordIndex": 6
              },
              {
                "text": "{H5927G}\\H9016",
                "wordIndex": 7,
                "lex": {
                  "code": "H5927",
                  "lemma": "עָלָה",
                  "translit": "a.lah",
                  "morph": "H:V",
                  "gloss": "to ascend: regurgitate : regurgitate/chew(cud)<br>1) to go up, ascend, climb<br>1a) (Qal)<br>1a1) to go up, ascend<br>1a2) to meet, visit, follow, depart, withdraw, retreat<br>1a3) to go up, come up (of animals)<br>1a4) to spring up, grow, shoot forth (of vegetation)<br>1a5) to go up, go up over, rise (of natural phenomenon)<br>1a6) to come up (before God)<br>1a7) to go up, go up over, extend (of boundary)<br>1a8) to excel, be superior to<br>1b) (Niphal)<br>1b1) to be taken up, be brought up, be taken away<br>1b2) to take oneself away<br>1b3) to be exalted<br>1c) (Hiphil)<br>1c1) to bring up, cause to ascend or climb, cause to go up<br>1c2) to bring up, bring against, take away<br>1c3) to bring up, draw up, train<br>1c4) to cause to ascend<br>1c5) to rouse, stir up (mentally)<br>1c6) to offer, bring up (of gifts)<br>1c7) to exalt<br>1c8) to cause to ascend, offer<br>1d) (Hophal)<br>1d1) to be carried away, be led up<br>1d2) to be taken up into, be inserted in<br>1d3) to be offered<br>1e) (Hithpael) to lift oneself",
                  "raw": "H5927\tH5927M = a Meaning of\tH5927G\tעָלָה\ta.lah\tH:V\tto ascend: regurgitate\t: regurgitate/chew(cud)<br>1) to go up, ascend, climb<br>1a) (Qal)<br>1a1) to go up, ascend<br>1a2) to meet, visit, follow, depart, withdraw, retreat<br>1a3) to go up, come up (of animals)<br>1a4) to spring up, grow, shoot forth (of vegetation)<br>1a5) to go up, go up over, rise (of natural phenomenon)<br>1a6) to come up (before God)<br>1a7) to go up, go up over, extend (of boundary)<br>1a8) to excel, be superior to<br>1b) (Niphal)<br>1b1) to be taken up, be brought up, be taken away<br>1b2) to take oneself away<br>1b3) to be exalted<br>1c) (Hiphil)<br>1c1) to bring up, cause to ascend or climb, cause to go up<br>1c2) to bring up, bring against, take away<br>1c3) to bring up, draw up, train<br>1c4) to cause to ascend<br>1c5) to rouse, stir up (mentally)<br>1c6) to offer, bring up (of gifts)<br>1c7) to exalt<br>1c8) to cause to ascend, offer<br>1d) (Hophal)<br>1d1) to be carried away, be led up<br>1d2) to be taken up into, be inserted in<br>1d3) to be offered<br>1e) (Hithpael) to lift oneself"
                }
              },
              {
                "text": "HVqi1cp",
                "wordIndex": 8
              },
              {
                "text": "H5927G",
                "wordIndex": 9,
                "lex": {
                  "code": "H5927",
                  "lemma": "עָלָה",
                  "translit": "a.lah",
                  "morph": "H:V",
                  "gloss": "to ascend: regurgitate : regurgitate/chew(cud)<br>1) to go up, ascend, climb<br>1a) (Qal)<br>1a1) to go up, ascend<br>1a2) to meet, visit, follow, depart, withdraw, retreat<br>1a3) to go up, come up (of animals)<br>1a4) to spring up, grow, shoot forth (of vegetation)<br>1a5) to go up, go up over, rise (of natural phenomenon)<br>1a6) to come up (before God)<br>1a7) to go up, go up over, extend (of boundary)<br>1a8) to excel, be superior to<br>1b) (Niphal)<br>1b1) to be taken up, be brought up, be taken away<br>1b2) to take oneself away<br>1b3) to be exalted<br>1c) (Hiphil)<br>1c1) to bring up, cause to ascend or climb, cause to go up<br>1c2) to bring up, bring against, take away<br>1c3) to bring up, draw up, train<br>1c4) to cause to ascend<br>1c5) to rouse, stir up (mentally)<br>1c6) to offer, bring up (of gifts)<br>1c7) to exalt<br>1c8) to cause to ascend, offer<br>1d) (Hophal)<br>1d1) to be carried away, be led up<br>1d2) to be taken up into, be inserted in<br>1d3) to be offered<br>1e) (Hithpael) to lift oneself",
                  "raw": "H5927\tH5927M = a Meaning of\tH5927G\tעָלָה\ta.lah\tH:V\tto ascend: regurgitate\t: regurgitate/chew(cud)<br>1) to go up, ascend, climb<br>1a) (Qal)<br>1a1) to go up, ascend<br>1a2) to meet, visit, follow, depart, withdraw, retreat<br>1a3) to go up, come up (of animals)<br>1a4) to spring up, grow, shoot forth (of vegetation)<br>1a5) to go up, go up over, rise (of natural phenomenon)<br>1a6) to come up (before God)<br>1a7) to go up, go up over, extend (of boundary)<br>1a8) to excel, be superior to<br>1b) (Niphal)<br>1b1) to be taken up, be brought up, be taken away<br>1b2) to take oneself away<br>1b3) to be exalted<br>1c) (Hiphil)<br>1c1) to bring up, cause to ascend or climb, cause to go up<br>1c2) to bring up, bring against, take away<br>1c3) to bring up, draw up, train<br>1c4) to cause to ascend<br>1c5) to rouse, stir up (mentally)<br>1c6) to offer, bring up (of gifts)<br>1c7) to exalt<br>1c8) to cause to ascend, offer<br>1d) (Hophal)<br>1d1) to be carried away, be led up<br>1d2) to be taken up into, be inserted in<br>1d3) to be offered<br>1e) (Hithpael) to lift oneself"
                }
              },
              {
                "text": "{H5927G=עָלָה=:",
                "wordIndex": 10,
                "lex": {
                  "code": "H5927",
                  "lemma": "עָלָה",
                  "translit": "a.lah",
                  "morph": "H:V",
                  "gloss": "to ascend: regurgitate : regurgitate/chew(cud)<br>1) to go up, ascend, climb<br>1a) (Qal)<br>1a1) to go up, ascend<br>1a2) to meet, visit, follow, depart, withdraw, retreat<br>1a3) to go up, come up (of animals)<br>1a4) to spring up, grow, shoot forth (of vegetation)<br>1a5) to go up, go up over, rise (of natural phenomenon)<br>1a6) to come up (before God)<br>1a7) to go up, go up over, extend (of boundary)<br>1a8) to excel, be superior to<br>1b) (Niphal)<br>1b1) to be taken up, be brought up, be taken away<br>1b2) to take oneself away<br>1b3) to be exalted<br>1c) (Hiphil)<br>1c1) to bring up, cause to ascend or climb, cause to go up<br>1c2) to bring up, bring against, take away<br>1c3) to bring up, draw up, train<br>1c4) to cause to ascend<br>1c5) to rouse, stir up (mentally)<br>1c6) to offer, bring up (of gifts)<br>1c7) to exalt<br>1c8) to cause to ascend, offer<br>1d) (Hophal)<br>1d1) to be carried away, be led up<br>1d2) to be taken up into, be inserted in<br>1d3) to be offered<br>1e) (Hithpael) to lift oneself",
                  "raw": "H5927\tH5927M = a Meaning of\tH5927G\tעָלָה\ta.lah\tH:V\tto ascend: regurgitate\t: regurgitate/chew(cud)<br>1) to go up, ascend, climb<br>1a) (Qal)<br>1a1) to go up, ascend<br>1a2) to meet, visit, follow, depart, withdraw, retreat<br>1a3) to go up, come up (of animals)<br>1a4) to spring up, grow, shoot forth (of vegetation)<br>1a5) to go up, go up over, rise (of natural phenomenon)<br>1a6) to come up (before God)<br>1a7) to go up, go up over, extend (of boundary)<br>1a8) to excel, be superior to<br>1b) (Niphal)<br>1b1) to be taken up, be brought up, be taken away<br>1b2) to take oneself away<br>1b3) to be exalted<br>1c) (Hiphil)<br>1c1) to bring up, cause to ascend or climb, cause to go up<br>1c2) to bring up, bring against, take away<br>1c3) to bring up, draw up, train<br>1c4) to cause to ascend<br>1c5) to rouse, stir up (mentally)<br>1c6) to offer, bring up (of gifts)<br>1c7) to exalt<br>1c8) to cause to ascend, offer<br>1d) (Hophal)<br>1d1) to be carried away, be led up<br>1d2) to be taken up into, be inserted in<br>1d3) to be offered<br>1e) (Hithpael) to lift oneself"
                }
              },
              {
                "text": "rise»to",
                "wordIndex": 11
              },
              {
                "text": "ascend:1_rise;_go}\\H9016=׃=verseEnd",
                "wordIndex": 12,
                "lex": {
                  "code": "H9016",
                  "lemma": ":",
                  "translit": ":",
                  "morph": "Punct.",
                  "gloss": "[.] Punctuation Sof-Pasuq: ends a verse",
                  "raw": "H9016\tH9016 =\tH9016\t:\t:\tPunct.\t[.]\tPunctuation Sof-Pasuq: ends a verse"
                }
              }
            ],
            "originalVerseText": "#19=L נַעֲלֶֽה\\׃ na.'a.Leh we will come up {H5927G}\\H9016 HVqi1cp H5927G {H5927G=עָלָה=: rise»to ascend:1_rise;_go}\\H9016=׃=verseEnd"
          }
        },
        {
          "chapter": 16,
          "verse": 15,
          "text": "Then Moses became very angry. He said to the Lord, “Don’t accept their offering. I haven’t taken even a donkey from them. In fact, I haven’t done anything wrong to any of them.”",
          "isHeading": false,
          "interlinear": {
            "tokens": [
              {
                "text": "#20=L",
                "wordIndex": 0
              },
              {
                "text": "מֵ/הֶֽם\\׃",
                "wordIndex": 1
              },
              {
                "text": "me./Hem",
                "wordIndex": 2
              },
              {
                "text": "of",
                "wordIndex": 3
              },
              {
                "text": "<the>/",
                "wordIndex": 4
              },
              {
                "text": "them",
                "wordIndex": 5
              },
              {
                "text": "H9006/{H9038}\\H9016",
                "wordIndex": 6,
                "lex": {
                  "code": "H9006",
                  "lemma": "/מ",
                  "translit": "m",
                  "morph": "Prefix",
                  "gloss": "from Prefix mem: from",
                  "raw": "H9006\tH9006 =\tH9006\t/מ\tm\tPrefix\tfrom\tPrefix mem: from"
                }
              },
              {
                "text": "HRd/Sp3mp",
                "wordIndex": 7
              },
              {
                "text": "H9038_B",
                "wordIndex": 8,
                "lex": {
                  "code": "H9038",
                  "lemma": "הֶם",
                  "translit": "hem",
                  "morph": "Op3m",
                  "gloss": "them Personal object pronoun -  suffix for propositions and verbs without an object: 3rd person masculine plural",
                  "raw": "H9038\tH9038 =\tH9038\tהֶם\them\tOp3m\tthem\tPersonal object pronoun -  suffix for propositions and verbs without an object: 3rd person masculine plural"
                }
              },
              {
                "text": "H9006=מ=from/{H9038=Op3m=them}\\H9016=׃=verseEnd",
                "wordIndex": 9,
                "lex": {
                  "code": "H9006",
                  "lemma": "/מ",
                  "translit": "m",
                  "morph": "Prefix",
                  "gloss": "from Prefix mem: from",
                  "raw": "H9006\tH9006 =\tH9006\t/מ\tm\tPrefix\tfrom\tPrefix mem: from"
                }
              }
            ],
            "originalVerseText": "#20=L מֵ/הֶֽם\\׃ me./Hem of <the>/ them H9006/{H9038}\\H9016 HRd/Sp3mp H9038_B H9006=מ=from/{H9038=Op3m=them}\\H9016=׃=verseEnd"
          }
        },
        {
          "chapter": 16,
          "verse": 16,
          "text": "Moses said to Korah, “You and all of your followers must stand in front of the Lord tomorrow. You must appear there along with Aaron.",
          "isHeading": false,
          "interlinear": {
            "tokens": [
              {
                "text": "#14=L",
                "wordIndex": 0
              },
              {
                "text": "מָחָֽר\\׃",
                "wordIndex": 1
              },
              {
                "text": "ma.Char",
                "wordIndex": 2
              },
              {
                "text": "tomorrow",
                "wordIndex": 3
              },
              {
                "text": "{H4279}\\H9016",
                "wordIndex": 4,
                "lex": {
                  "code": "H4279",
                  "lemma": "מָחָר",
                  "translit": "ma.char",
                  "morph": "H:N-M",
                  "gloss": "tomorrow 1) tomorrow, in time to come, in the future<br>1a) tomorrow (as the day following the present day)<br>1b) in future time",
                  "raw": "H4279\tH4279 =\tH4279\tמָחָר\tma.char\tH:N-M\ttomorrow\t1) tomorrow, in time to come, in the future<br>1a) tomorrow (as the day following the present day)<br>1b) in future time"
                }
              },
              {
                "text": "HNcmsa",
                "wordIndex": 5
              },
              {
                "text": "H4279",
                "wordIndex": 6,
                "lex": {
                  "code": "H4279",
                  "lemma": "מָחָר",
                  "translit": "ma.char",
                  "morph": "H:N-M",
                  "gloss": "tomorrow 1) tomorrow, in time to come, in the future<br>1a) tomorrow (as the day following the present day)<br>1b) in future time",
                  "raw": "H4279\tH4279 =\tH4279\tמָחָר\tma.char\tH:N-M\ttomorrow\t1) tomorrow, in time to come, in the future<br>1a) tomorrow (as the day following the present day)<br>1b) in future time"
                }
              },
              {
                "text": "{H4279=מָחָר=tomorrow}\\H9016=׃=verseEnd",
                "wordIndex": 7,
                "lex": {
                  "code": "H4279",
                  "lemma": "מָחָר",
                  "translit": "ma.char",
                  "morph": "H:N-M",
                  "gloss": "tomorrow 1) tomorrow, in time to come, in the future<br>1a) tomorrow (as the day following the present day)<br>1b) in future time",
                  "raw": "H4279\tH4279 =\tH4279\tמָחָר\tma.char\tH:N-M\ttomorrow\t1) tomorrow, in time to come, in the future<br>1a) tomorrow (as the day following the present day)<br>1b) in future time"
                }
              }
            ],
            "originalVerseText": "#14=L מָחָֽר\\׃ ma.Char tomorrow {H4279}\\H9016 HNcmsa H4279 {H4279=מָחָר=tomorrow}\\H9016=׃=verseEnd"
          }
        },
        {
          "chapter": 16,
          "verse": 17,
          "text": "Each man must get his shallow cup. He must put incense in it. There will be a total of 250 incense cups. Each man must bring his cup to the Lord. You and Aaron must also bring your cups.”",
          "isHeading": false,
          "interlinear": {
            "tokens": [
              {
                "text": "#18=L",
                "wordIndex": 0
              },
              {
                "text": "מַחְתָּתֽ/וֹ\\׃",
                "wordIndex": 1
              },
              {
                "text": "mach.ta.T/o",
                "wordIndex": 2
              },
              {
                "text": "censer/",
                "wordIndex": 3
              },
              {
                "text": "his",
                "wordIndex": 4
              },
              {
                "text": "{H4289}/H9023\\H9016",
                "wordIndex": 5,
                "lex": {
                  "code": "H4289",
                  "lemma": "מַחְתָּה",
                  "translit": "mach.tah",
                  "morph": "H:N-F",
                  "gloss": "censer 1) fire-holder, censer, firepan, snuff dish, tray<br>1a) snuff-dish<br>1b) fire-pans<br>1c) censer",
                  "raw": "H4289\tH4289 =\tH4289\tמַחְתָּה\tmach.tah\tH:N-F\tcenser\t1) fire-holder, censer, firepan, snuff dish, tray<br>1a) snuff-dish<br>1b) fire-pans<br>1c) censer"
                }
              },
              {
                "text": "HNcfsc/Sp3ms",
                "wordIndex": 6
              },
              {
                "text": "H4289_D",
                "wordIndex": 7,
                "lex": {
                  "code": "H4289",
                  "lemma": "מַחְתָּה",
                  "translit": "mach.tah",
                  "morph": "H:N-F",
                  "gloss": "censer 1) fire-holder, censer, firepan, snuff dish, tray<br>1a) snuff-dish<br>1b) fire-pans<br>1c) censer",
                  "raw": "H4289\tH4289 =\tH4289\tמַחְתָּה\tmach.tah\tH:N-F\tcenser\t1) fire-holder, censer, firepan, snuff dish, tray<br>1a) snuff-dish<br>1b) fire-pans<br>1c) censer"
                }
              },
              {
                "text": "{H4289=מַחְתָּה=censer}/H9023=Ps3m=his\\H9016=׃=verseEnd",
                "wordIndex": 8,
                "lex": {
                  "code": "H4289",
                  "lemma": "מַחְתָּה",
                  "translit": "mach.tah",
                  "morph": "H:N-F",
                  "gloss": "censer 1) fire-holder, censer, firepan, snuff dish, tray<br>1a) snuff-dish<br>1b) fire-pans<br>1c) censer",
                  "raw": "H4289\tH4289 =\tH4289\tמַחְתָּה\tmach.tah\tH:N-F\tcenser\t1) fire-holder, censer, firepan, snuff dish, tray<br>1a) snuff-dish<br>1b) fire-pans<br>1c) censer"
                }
              }
            ],
            "originalVerseText": "#18=L מַחְתָּתֽ/וֹ\\׃ mach.ta.T/o censer/ his {H4289}/H9023\\H9016 HNcfsc/Sp3ms H4289_D {H4289=מַחְתָּה=censer}/H9023=Ps3m=his\\H9016=׃=verseEnd"
          }
        },
        {
          "chapter": 16,
          "verse": 18,
          "text": "So each man got his cup. He put fire and incense in it. All of the men came with Moses and Aaron. They stood at the entrance to the Tent of Meeting.",
          "isHeading": false,
          "interlinear": {
            "tokens": [
              {
                "text": "#15=L",
                "wordIndex": 0
              },
              {
                "text": "וְ/אַהֲרֹֽן\\׃",
                "wordIndex": 1
              },
              {
                "text": "ve./'a.ha.Ron",
                "wordIndex": 2
              },
              {
                "text": "and/",
                "wordIndex": 3
              },
              {
                "text": "Aaron",
                "wordIndex": 4
              },
              {
                "text": "H9002/{H0175}\\H9016",
                "wordIndex": 5,
                "lex": {
                  "code": "H9002",
                  "lemma": "/וְ",
                  "translit": "v",
                  "morph": "H:Conj",
                  "gloss": "and Conjunctive vav -  i.e. followed by prefix, suffix or non-verb (conjunctive) (‘and/but’)",
                  "raw": "H9002\tH9002 =\tH9002\t/וְ\tv\tH:Conj\tand\tConjunctive vav -  i.e. followed by prefix, suffix or non-verb (conjunctive) (‘and/but’)"
                }
              },
              {
                "text": "HC/Npm",
                "wordIndex": 6
              },
              {
                "text": "H0175",
                "wordIndex": 7,
                "lex": {
                  "code": "H0175",
                  "lemma": "אַהֲרֹן",
                  "translit": "a.ha.ron",
                  "morph": "N:N-M-P",
                  "gloss": "Aaron A man of the tribe of Levi living at the time of Egypt and Wilderness, first mentioned at Exo.4.14; <br> son of: Amram (H6019) and Jochebed (H3115); <br> brother of: Moses (H4872) and Miriam (H4813); married to Elisheba (H0472); <br> father of: Nadab (H5070), Abihu (H0030), Eleazar (H0499) and Ithamar (H0385)<BR>Also named: <i>Aarōn</i> (Ἀαρών \"Aaron\" G0002) <BR> § Aaron = \"light bringer\"<br> brother of Moses, a Levite and the first high priest<br>",
                  "raw": "H0175\tH0175 =\tH0175\tאַהֲרֹן\ta.ha.ron\tN:N-M-P\tAaron\tA man of the tribe of Levi living at the time of Egypt and Wilderness, first mentioned at Exo.4.14; <br> son of: Amram (H6019) and Jochebed (H3115); <br> brother of: Moses (H4872) and Miriam (H4813); married to Elisheba (H0472); <br> father of: Nadab (H5070), Abihu (H0030), Eleazar (H0499) and Ithamar (H0385)<BR>Also named: <i>Aarōn</i> (Ἀαρών \"Aaron\" G0002) <BR> § Aaron = \"light bringer\"<br> brother of Moses, a Levite and the first high priest<br>"
                }
              },
              {
                "text": "H9002=ו=and/{H0175=אַהֲרֹן=Aaron»Aaron@Exo.4.14-Heb}\\H9016=׃=verseEnd",
                "wordIndex": 8,
                "lex": {
                  "code": "H9002",
                  "lemma": "/וְ",
                  "translit": "v",
                  "morph": "H:Conj",
                  "gloss": "and Conjunctive vav -  i.e. followed by prefix, suffix or non-verb (conjunctive) (‘and/but’)",
                  "raw": "H9002\tH9002 =\tH9002\t/וְ\tv\tH:Conj\tand\tConjunctive vav -  i.e. followed by prefix, suffix or non-verb (conjunctive) (‘and/but’)"
                }
              }
            ],
            "originalVerseText": "#15=L וְ/אַהֲרֹֽן\\׃ ve./'a.ha.Ron and/ Aaron H9002/{H0175}\\H9016 HC/Npm H0175 H9002=ו=and/{H0175=אַהֲרֹן=Aaron»Aaron@Exo.4.14-Heb}\\H9016=׃=verseEnd"
          }
        },
        {
          "chapter": 16,
          "verse": 19,
          "text": "Korah gathered all of his followers together at the entrance to the tent. They opposed Moses and Aaron.\nThen the glory of the Lord appeared to the whole community.",
          "isHeading": false,
          "interlinear": {
            "tokens": [
              {
                "text": "#16=L",
                "wordIndex": 0
              },
              {
                "text": "הָ/עֵדָֽה\\׃\\",
                "wordIndex": 1
              },
              {
                "text": "\\פ",
                "wordIndex": 2
              },
              {
                "text": "ha./'e.Dah",
                "wordIndex": 3
              },
              {
                "text": "the/",
                "wordIndex": 4
              },
              {
                "text": "congregation",
                "wordIndex": 5
              },
              {
                "text": "H9009/{H5712}\\H9016\\",
                "wordIndex": 6,
                "lex": {
                  "code": "H9009",
                  "lemma": "/ה",
                  "translit": "ha",
                  "morph": "Prefix",
                  "gloss": "[the] Prefix hé article: \"the\" for a subject, not object",
                  "raw": "H9009\tH9009 =\tH9009\t/ה\tha\tPrefix\t[the]\tPrefix hé article: \"the\" for a subject, not object"
                }
              },
              {
                "text": "\\H9017",
                "wordIndex": 7,
                "lex": {
                  "code": "H9017",
                  "lemma": "פ",
                  "translit": "P",
                  "morph": "Punct.",
                  "gloss": "[¶] Punctuation Pe paragraph: ends a literary section",
                  "raw": "H9017\tH9017 =\tH9017\tפ\tP\tPunct.\t[¶]\tPunctuation Pe paragraph: ends a literary section"
                }
              },
              {
                "text": "HTd/Ncfsa",
                "wordIndex": 8
              },
              {
                "text": "H5712_B",
                "wordIndex": 9,
                "lex": {
                  "code": "H5712",
                  "lemma": "עֵדָה",
                  "translit": "e.dah",
                  "morph": "H:N-F",
                  "gloss": "congregation congregation, gathering",
                  "raw": "H5712\tH5712 =\tH5712\tעֵדָה\te.dah\tH:N-F\tcongregation\tcongregation, gathering"
                }
              },
              {
                "text": "H9009=ה=the/{H5712=עֵדָה=congregation}\\H9016=׃=verseEnd\\",
                "wordIndex": 10,
                "lex": {
                  "code": "H9009",
                  "lemma": "/ה",
                  "translit": "ha",
                  "morph": "Prefix",
                  "gloss": "[the] Prefix hé article: \"the\" for a subject, not object",
                  "raw": "H9009\tH9009 =\tH9009\t/ה\tha\tPrefix\t[the]\tPrefix hé article: \"the\" for a subject, not object"
                }
              },
              {
                "text": "\\H9017=פ=para",
                "wordIndex": 11,
                "lex": {
                  "code": "H9017",
                  "lemma": "פ",
                  "translit": "P",
                  "morph": "Punct.",
                  "gloss": "[¶] Punctuation Pe paragraph: ends a literary section",
                  "raw": "H9017\tH9017 =\tH9017\tפ\tP\tPunct.\t[¶]\tPunctuation Pe paragraph: ends a literary section"
                }
              }
            ],
            "originalVerseText": "#16=L הָ/עֵדָֽה\\׃\\ \\פ ha./'e.Dah the/ congregation H9009/{H5712}\\H9016\\ \\H9017 HTd/Ncfsa H5712_B H9009=ה=the/{H5712=עֵדָה=congregation}\\H9016=׃=verseEnd\\ \\H9017=פ=para"
          }
        }
      ]
    }
  },
  "gospel": {
    "passage": "?",
    "versions": {
      "leb": [],
      "nirv": []
    }
  }
}