{
  "torah": {
    "passage": "Deuteronomy 33:22 - 33:26",
    "versions": {
      "leb": [
        {
          "chapter": 33,
          "verse": 22,
          "text": "“Dan is a cub of a lion;\nhe leaps from Bashan.”",
          "isHeading": true,
          "interlinear": {
            "tokens": [
              {
                "text": "#08=L",
                "wordIndex": 0
              },
              {
                "text": "הַ/בָּשָֽׁן\\׃",
                "wordIndex": 1
              },
              {
                "text": "ha./ba.Shan",
                "wordIndex": 2
              },
              {
                "text": "<the>/",
                "wordIndex": 3
              },
              {
                "text": "Bashan",
                "wordIndex": 4
              },
              {
                "text": "H9009/{H1316}\\H9016",
                "wordIndex": 5,
                "lex": {
                  "code": "H9009",
                  "lemma": "/ה",
                  "translit": "ha",
                  "morph": "Prefix",
                  "gloss": "[the] Prefix hé article: \"the\" for a subject, not object",
                  "raw": "H9009\tH9009 =\tH9009\t/ה\tha\tPrefix\t[the]\tPrefix hé article: \"the\" for a subject, not object"
                }
              },
              {
                "text": "HTd/Npl",
                "wordIndex": 6
              },
              {
                "text": "H1316",
                "wordIndex": 7,
                "lex": {
                  "code": "H1316",
                  "lemma": "בָּשָׁן",
                  "translit": "ba.shan",
                  "morph": "N:N--L",
                  "gloss": "Bashan <BR> § Bashan = \"fruitful\"<br> a district east of the Jordan known for its fertility which was given to the half-tribe of Manasseh<br>",
                  "raw": "H1316\tH1316 =\tH1316\tבָּשָׁן\tba.shan\tN:N--L\tBashan\t <BR> § Bashan = \"fruitful\"<br> a district east of the Jordan known for its fertility which was given to the half-tribe of Manasseh<br>"
                }
              },
              {
                "text": "H9009=ה=the/{H1316=בָּשָׁן=Bashan»Bashan@Num.21.33-Zec}\\H9016=׃=verseEnd",
                "wordIndex": 8,
                "lex": {
                  "code": "H9009",
                  "lemma": "/ה",
                  "translit": "ha",
                  "morph": "Prefix",
                  "gloss": "[the] Prefix hé article: \"the\" for a subject, not object",
                  "raw": "H9009\tH9009 =\tH9009\t/ה\tha\tPrefix\t[the]\tPrefix hé article: \"the\" for a subject, not object"
                }
              }
            ],
            "originalVerseText": "#08=L הַ/בָּשָֽׁן\\׃ ha./ba.Shan <the>/ Bashan H9009/{H1316}\\H9016 HTd/Npl H1316 H9009=ה=the/{H1316=בָּשָׁן=Bashan»Bashan@Num.21.33-Zec}\\H9016=׃=verseEnd"
          }
        },
        {
          "chapter": 33,
          "verse": 23,
          "text": "“Oh, Naphtali, sated of favor,\nand full of the blessing of Yahweh;\ntake possession of the lake,\nand the land to the south.”",
          "isHeading": true,
          "interlinear": {
            "tokens": [
              {
                "text": "#11=L",
                "wordIndex": 0
              },
              {
                "text": "יְרָֽשָׁ/ה\\׃\\",
                "wordIndex": 1
              },
              {
                "text": "\\ס",
                "wordIndex": 2
              },
              {
                "text": "ye.Ra.sha/h",
                "wordIndex": 3
              },
              {
                "text": "take",
                "wordIndex": 4
              },
              {
                "text": "possession",
                "wordIndex": 5
              },
              {
                "text": "of/",
                "wordIndex": 6
              },
              {
                "text": "!",
                "wordIndex": 7
              },
              {
                "text": "{H3423H}/H9012\\H9016\\",
                "wordIndex": 8,
                "lex": {
                  "code": "H3423",
                  "lemma": "יָרַשׁ",
                  "translit": "ya.rash",
                  "morph": "H:V",
                  "gloss": "to possess: poor : poor/conquered<br>1) to seize, dispossess, take possession off, inherit, disinherit, occupy, impoverish, be an heir<br>1a) (Qal)<br>1a1) to take possession of<br>1a2) to inherit<br>1a3) to impoverish, come to poverty, be poor<br>1b) (Niphal) to be dispossessed, be impoverished, come to poverty<br>1c) (Piel) to devour<br>1d) (Hiphil)<br>1d1) to cause to possess or inherit<br>1d2) to cause others to possess or inherit<br>1d3) to impoverish<br>1d4) to dispossess<br>1d5) to destroy, bring to ruin, disinherit",
                  "raw": "H3423\tH3423I = a Meaning of\tH3423G\tיָרַשׁ\tya.rash\tH:V\tto possess: poor\t: poor/conquered<br>1) to seize, dispossess, take possession off, inherit, disinherit, occupy, impoverish, be an heir<br>1a) (Qal)<br>1a1) to take possession of<br>1a2) to inherit<br>1a3) to impoverish, come to poverty, be poor<br>1b) (Niphal) to be dispossessed, be impoverished, come to poverty<br>1c) (Piel) to devour<br>1d) (Hiphil)<br>1d1) to cause to possess or inherit<br>1d2) to cause others to possess or inherit<br>1d3) to impoverish<br>1d4) to dispossess<br>1d5) to destroy, bring to ruin, disinherit"
                }
              },
              {
                "text": "\\H9018",
                "wordIndex": 9,
                "lex": {
                  "code": "H9018",
                  "lemma": "ס",
                  "translit": "S",
                  "morph": "Punct.",
                  "gloss": "[¶] Punctuation Sameq paragraph: ends a lectionary section",
                  "raw": "H9018\tH9018 =\tH9018\tס\tS\tPunct.\t[¶]\tPunctuation Sameq paragraph: ends a lectionary section"
                }
              },
              {
                "text": "HVqv2ms/Sh",
                "wordIndex": 10
              },
              {
                "text": "H3423H",
                "wordIndex": 11,
                "lex": {
                  "code": "H3423",
                  "lemma": "יָרַשׁ",
                  "translit": "ya.rash",
                  "morph": "H:V",
                  "gloss": "to possess: poor : poor/conquered<br>1) to seize, dispossess, take possession off, inherit, disinherit, occupy, impoverish, be an heir<br>1a) (Qal)<br>1a1) to take possession of<br>1a2) to inherit<br>1a3) to impoverish, come to poverty, be poor<br>1b) (Niphal) to be dispossessed, be impoverished, come to poverty<br>1c) (Piel) to devour<br>1d) (Hiphil)<br>1d1) to cause to possess or inherit<br>1d2) to cause others to possess or inherit<br>1d3) to impoverish<br>1d4) to dispossess<br>1d5) to destroy, bring to ruin, disinherit",
                  "raw": "H3423\tH3423I = a Meaning of\tH3423G\tיָרַשׁ\tya.rash\tH:V\tto possess: poor\t: poor/conquered<br>1) to seize, dispossess, take possession off, inherit, disinherit, occupy, impoverish, be an heir<br>1a) (Qal)<br>1a1) to take possession of<br>1a2) to inherit<br>1a3) to impoverish, come to poverty, be poor<br>1b) (Niphal) to be dispossessed, be impoverished, come to poverty<br>1c) (Piel) to devour<br>1d) (Hiphil)<br>1d1) to cause to possess or inherit<br>1d2) to cause others to possess or inherit<br>1d3) to impoverish<br>1d4) to dispossess<br>1d5) to destroy, bring to ruin, disinherit"
                }
              },
              {
                "text": "{H3423H=יָרַשׁ=:",
                "wordIndex": 12,
                "lex": {
                  "code": "H3423",
                  "lemma": "יָרַשׁ",
                  "translit": "ya.rash",
                  "morph": "H:V",
                  "gloss": "to possess: poor : poor/conquered<br>1) to seize, dispossess, take possession off, inherit, disinherit, occupy, impoverish, be an heir<br>1a) (Qal)<br>1a1) to take possession of<br>1a2) to inherit<br>1a3) to impoverish, come to poverty, be poor<br>1b) (Niphal) to be dispossessed, be impoverished, come to poverty<br>1c) (Piel) to devour<br>1d) (Hiphil)<br>1d1) to cause to possess or inherit<br>1d2) to cause others to possess or inherit<br>1d3) to impoverish<br>1d4) to dispossess<br>1d5) to destroy, bring to ruin, disinherit",
                  "raw": "H3423\tH3423I = a Meaning of\tH3423G\tיָרַשׁ\tya.rash\tH:V\tto possess: poor\t: poor/conquered<br>1) to seize, dispossess, take possession off, inherit, disinherit, occupy, impoverish, be an heir<br>1a) (Qal)<br>1a1) to take possession of<br>1a2) to inherit<br>1a3) to impoverish, come to poverty, be poor<br>1b) (Niphal) to be dispossessed, be impoverished, come to poverty<br>1c) (Piel) to devour<br>1d) (Hiphil)<br>1d1) to cause to possess or inherit<br>1d2) to cause others to possess or inherit<br>1d3) to impoverish<br>1d4) to dispossess<br>1d5) to destroy, bring to ruin, disinherit"
                }
              },
              {
                "text": "take»to",
                "wordIndex": 13
              },
              {
                "text": "possess:2_take;_conquer;_drive_out}/H9012=ה=emph.\\H9016=׃=verseEnd\\",
                "wordIndex": 14,
                "lex": {
                  "code": "H9012",
                  "lemma": "ה/",
                  "translit": "h",
                  "morph": "Suffix",
                  "gloss": "[emph.?] Suffix  hé – paragogic: adds emphasis",
                  "raw": "H9012\tH9012 =\tH9012\tה/\th\tSuffix\t[emph.?]\tSuffix  hé – paragogic: adds emphasis"
                }
              },
              {
                "text": "\\H9018=ס=section",
                "wordIndex": 15,
                "lex": {
                  "code": "H9018",
                  "lemma": "ס",
                  "translit": "S",
                  "morph": "Punct.",
                  "gloss": "[¶] Punctuation Sameq paragraph: ends a lectionary section",
                  "raw": "H9018\tH9018 =\tH9018\tס\tS\tPunct.\t[¶]\tPunctuation Sameq paragraph: ends a lectionary section"
                }
              }
            ],
            "originalVerseText": "#11=L יְרָֽשָׁ/ה\\׃\\ \\ס ye.Ra.sha/h take possession of/ ! {H3423H}/H9012\\H9016\\ \\H9018 HVqv2ms/Sh H3423H {H3423H=יָרַשׁ=: take»to possess:2_take;_conquer;_drive_out}/H9012=ה=emph.\\H9016=׃=verseEnd\\ \\H9018=ס=section"
          }
        },
        {
          "chapter": 33,
          "verse": 24,
          "text": "“Blessed more than sons is Asher;\nmay he be the favorite of his brothers,\ndipping his feet in the oil.",
          "isHeading": true,
          "interlinear": {
            "tokens": [
              {
                "text": "#11=L",
                "wordIndex": 0
              },
              {
                "text": "רַגְלֽ/וֹ\\׃",
                "wordIndex": 1
              },
              {
                "text": "rag.L/o",
                "wordIndex": 2
              },
              {
                "text": "foot/",
                "wordIndex": 3
              },
              {
                "text": "his",
                "wordIndex": 4
              },
              {
                "text": "{H7272}/H9023\\H9016",
                "wordIndex": 5,
                "lex": {
                  "code": "H7272",
                  "lemma": "רֶ֫גֶל",
                  "translit": "re.gel",
                  "morph": "H:N-F",
                  "gloss": "foot 1) foot<br>1a) foot, leg<br>1b) of God (anthropomorphic)<br>1c) of seraphim, cherubim, idols, animals, table<br>1d) according to the pace of (with prep)<br>1e) three times (feet, paces)<BR>Aramaic equivalent: <i>re.gal</i> (רְגַל \"foot\" H7271)",
                  "raw": "H7272\tH7272 =\tH7272\tרֶ֫גֶל\tre.gel\tH:N-F\tfoot\t1) foot<br>1a) foot, leg<br>1b) of God (anthropomorphic)<br>1c) of seraphim, cherubim, idols, animals, table<br>1d) according to the pace of (with prep)<br>1e) three times (feet, paces)<BR>Aramaic equivalent: <i>re.gal</i> (רְגַל \"foot\" H7271)"
                }
              },
              {
                "text": "HNcfsc/Sp3ms",
                "wordIndex": 6
              },
              {
                "text": "H7272",
                "wordIndex": 7,
                "lex": {
                  "code": "H7272",
                  "lemma": "רֶ֫גֶל",
                  "translit": "re.gel",
                  "morph": "H:N-F",
                  "gloss": "foot 1) foot<br>1a) foot, leg<br>1b) of God (anthropomorphic)<br>1c) of seraphim, cherubim, idols, animals, table<br>1d) according to the pace of (with prep)<br>1e) three times (feet, paces)<BR>Aramaic equivalent: <i>re.gal</i> (רְגַל \"foot\" H7271)",
                  "raw": "H7272\tH7272 =\tH7272\tרֶ֫גֶל\tre.gel\tH:N-F\tfoot\t1) foot<br>1a) foot, leg<br>1b) of God (anthropomorphic)<br>1c) of seraphim, cherubim, idols, animals, table<br>1d) according to the pace of (with prep)<br>1e) three times (feet, paces)<BR>Aramaic equivalent: <i>re.gal</i> (רְגַל \"foot\" H7271)"
                }
              },
              {
                "text": "{H7272=רֶ֫גֶל=foot}/H9023=Ps3m=his\\H9016=׃=verseEnd",
                "wordIndex": 8,
                "lex": {
                  "code": "H7272",
                  "lemma": "רֶ֫גֶל",
                  "translit": "re.gel",
                  "morph": "H:N-F",
                  "gloss": "foot 1) foot<br>1a) foot, leg<br>1b) of God (anthropomorphic)<br>1c) of seraphim, cherubim, idols, animals, table<br>1d) according to the pace of (with prep)<br>1e) three times (feet, paces)<BR>Aramaic equivalent: <i>re.gal</i> (רְגַל \"foot\" H7271)",
                  "raw": "H7272\tH7272 =\tH7272\tרֶ֫גֶל\tre.gel\tH:N-F\tfoot\t1) foot<br>1a) foot, leg<br>1b) of God (anthropomorphic)<br>1c) of seraphim, cherubim, idols, animals, table<br>1d) according to the pace of (with prep)<br>1e) three times (feet, paces)<BR>Aramaic equivalent: <i>re.gal</i> (רְגַל \"foot\" H7271)"
                }
              }
            ],
            "originalVerseText": "#11=L רַגְלֽ/וֹ\\׃ rag.L/o foot/ his {H7272}/H9023\\H9016 HNcfsc/Sp3ms H7272 {H7272=רֶ֫גֶל=foot}/H9023=Ps3m=his\\H9016=׃=verseEnd"
          }
        },
        {
          "chapter": 33,
          "verse": 25,
          "text": "and as your days, so is your strength.”",
          "isHeading": false,
          "interlinear": {
            "tokens": [
              {
                "text": "#05=L",
                "wordIndex": 0
              },
              {
                "text": "דָּבְאֶֽ/ךָ\\׃",
                "wordIndex": 1
              },
              {
                "text": "da.ve.'E./kha",
                "wordIndex": 2
              },
              {
                "text": "strength/",
                "wordIndex": 3
              },
              {
                "text": "your",
                "wordIndex": 4
              },
              {
                "text": "{H1679}/H9021\\H9016",
                "wordIndex": 5,
                "lex": {
                  "code": "H1679",
                  "lemma": "דֹּ֫בֶא",
                  "translit": "do.ve",
                  "morph": "H:N-M",
                  "gloss": "strength strength?, rest? (meaning obscure)",
                  "raw": "H1679\tH1679 =\tH1679\tדֹּ֫בֶא\tdo.ve\tH:N-M\tstrength\tstrength?, rest? (meaning obscure)"
                }
              },
              {
                "text": "HNcmsc/Sp2ms",
                "wordIndex": 6
              },
              {
                "text": "H1679",
                "wordIndex": 7,
                "lex": {
                  "code": "H1679",
                  "lemma": "דֹּ֫בֶא",
                  "translit": "do.ve",
                  "morph": "H:N-M",
                  "gloss": "strength strength?, rest? (meaning obscure)",
                  "raw": "H1679\tH1679 =\tH1679\tדֹּ֫בֶא\tdo.ve\tH:N-M\tstrength\tstrength?, rest? (meaning obscure)"
                }
              },
              {
                "text": "{H1679=דֹּ֫בֶא=rest}/H9021=Ps2m=your\\H9016=׃=verseEnd",
                "wordIndex": 8,
                "lex": {
                  "code": "H1679",
                  "lemma": "דֹּ֫בֶא",
                  "translit": "do.ve",
                  "morph": "H:N-M",
                  "gloss": "strength strength?, rest? (meaning obscure)",
                  "raw": "H1679\tH1679 =\tH1679\tדֹּ֫בֶא\tdo.ve\tH:N-M\tstrength\tstrength?, rest? (meaning obscure)"
                }
              }
            ],
            "originalVerseText": "#05=L דָּבְאֶֽ/ךָ\\׃ da.ve.'E./kha strength/ your {H1679}/H9021\\H9016 HNcmsc/Sp2ms H1679 {H1679=דֹּ֫בֶא=rest}/H9021=Ps2m=your\\H9016=׃=verseEnd"
          }
        },
        {
          "chapter": 33,
          "verse": 26,
          "text": "who rides through the heavens to your help,\nand with his majesty through the skies.",
          "isHeading": true,
          "interlinear": {
            "tokens": [
              {
                "text": "#08=L",
                "wordIndex": 0
              },
              {
                "text": "שְׁחָקִֽים\\׃",
                "wordIndex": 1
              },
              {
                "text": "she.cha.Kim",
                "wordIndex": 2
              },
              {
                "text": "clouds",
                "wordIndex": 3
              },
              {
                "text": "{H7834}\\H9016",
                "wordIndex": 4,
                "lex": {
                  "code": "H7834",
                  "lemma": "שַׁ֫חַק",
                  "translit": "sha.chaq",
                  "morph": "H:N-M",
                  "gloss": "cloud 1) dust, cloud<br>1a) fine dust<br>1b) (thin) cloud",
                  "raw": "H7834\tH7834 =\tH7834\tשַׁ֫חַק\tsha.chaq\tH:N-M\tcloud\t1) dust, cloud<br>1a) fine dust<br>1b) (thin) cloud"
                }
              },
              {
                "text": "HNcmpa",
                "wordIndex": 5
              },
              {
                "text": "H7834",
                "wordIndex": 6,
                "lex": {
                  "code": "H7834",
                  "lemma": "שַׁ֫חַק",
                  "translit": "sha.chaq",
                  "morph": "H:N-M",
                  "gloss": "cloud 1) dust, cloud<br>1a) fine dust<br>1b) (thin) cloud",
                  "raw": "H7834\tH7834 =\tH7834\tשַׁ֫חַק\tsha.chaq\tH:N-M\tcloud\t1) dust, cloud<br>1a) fine dust<br>1b) (thin) cloud"
                }
              },
              {
                "text": "{H7834=שַׁ֫חַק=cloud}\\H9016=׃=verseEnd",
                "wordIndex": 7,
                "lex": {
                  "code": "H7834",
                  "lemma": "שַׁ֫חַק",
                  "translit": "sha.chaq",
                  "morph": "H:N-M",
                  "gloss": "cloud 1) dust, cloud<br>1a) fine dust<br>1b) (thin) cloud",
                  "raw": "H7834\tH7834 =\tH7834\tשַׁ֫חַק\tsha.chaq\tH:N-M\tcloud\t1) dust, cloud<br>1a) fine dust<br>1b) (thin) cloud"
                }
              }
            ],
            "originalVerseText": "#08=L שְׁחָקִֽים\\׃ she.cha.Kim clouds {H7834}\\H9016 HNcmpa H7834 {H7834=שַׁ֫חַק=cloud}\\H9016=׃=verseEnd"
          }
        }
      ],
      "nirv": [
        {
          "chapter": 33,
          "verse": 22,
          "text": "Here’s what Moses said about Dan.\n“Dan is like a lion’s cub\nthat charges out of the land of Bashan.”",
          "isHeading": false,
          "interlinear": {
            "tokens": [
              {
                "text": "#08=L",
                "wordIndex": 0
              },
              {
                "text": "הַ/בָּשָֽׁן\\׃",
                "wordIndex": 1
              },
              {
                "text": "ha./ba.Shan",
                "wordIndex": 2
              },
              {
                "text": "<the>/",
                "wordIndex": 3
              },
              {
                "text": "Bashan",
                "wordIndex": 4
              },
              {
                "text": "H9009/{H1316}\\H9016",
                "wordIndex": 5,
                "lex": {
                  "code": "H9009",
                  "lemma": "/ה",
                  "translit": "ha",
                  "morph": "Prefix",
                  "gloss": "[the] Prefix hé article: \"the\" for a subject, not object",
                  "raw": "H9009\tH9009 =\tH9009\t/ה\tha\tPrefix\t[the]\tPrefix hé article: \"the\" for a subject, not object"
                }
              },
              {
                "text": "HTd/Npl",
                "wordIndex": 6
              },
              {
                "text": "H1316",
                "wordIndex": 7,
                "lex": {
                  "code": "H1316",
                  "lemma": "בָּשָׁן",
                  "translit": "ba.shan",
                  "morph": "N:N--L",
                  "gloss": "Bashan <BR> § Bashan = \"fruitful\"<br> a district east of the Jordan known for its fertility which was given to the half-tribe of Manasseh<br>",
                  "raw": "H1316\tH1316 =\tH1316\tבָּשָׁן\tba.shan\tN:N--L\tBashan\t <BR> § Bashan = \"fruitful\"<br> a district east of the Jordan known for its fertility which was given to the half-tribe of Manasseh<br>"
                }
              },
              {
                "text": "H9009=ה=the/{H1316=בָּשָׁן=Bashan»Bashan@Num.21.33-Zec}\\H9016=׃=verseEnd",
                "wordIndex": 8,
                "lex": {
                  "code": "H9009",
                  "lemma": "/ה",
                  "translit": "ha",
                  "morph": "Prefix",
                  "gloss": "[the] Prefix hé article: \"the\" for a subject, not object",
                  "raw": "H9009\tH9009 =\tH9009\t/ה\tha\tPrefix\t[the]\tPrefix hé article: \"the\" for a subject, not object"
                }
              }
            ],
            "originalVerseText": "#08=L הַ/בָּשָֽׁן\\׃ ha./ba.Shan <the>/ Bashan H9009/{H1316}\\H9016 HTd/Npl H1316 H9009=ה=the/{H1316=בָּשָׁן=Bashan»Bashan@Num.21.33-Zec}\\H9016=׃=verseEnd"
          }
        },
        {
          "chapter": 33,
          "verse": 23,
          "text": "Here’s what Moses said about Naphtali.\n“The Lord greatly favors Naphtali.\nThe Lord fills him with his blessing.\nNaphtali’s land will reach south to the Sea of Galilee.”",
          "isHeading": false,
          "interlinear": {
            "tokens": [
              {
                "text": "#11=L",
                "wordIndex": 0
              },
              {
                "text": "יְרָֽשָׁ/ה\\׃\\",
                "wordIndex": 1
              },
              {
                "text": "\\ס",
                "wordIndex": 2
              },
              {
                "text": "ye.Ra.sha/h",
                "wordIndex": 3
              },
              {
                "text": "take",
                "wordIndex": 4
              },
              {
                "text": "possession",
                "wordIndex": 5
              },
              {
                "text": "of/",
                "wordIndex": 6
              },
              {
                "text": "!",
                "wordIndex": 7
              },
              {
                "text": "{H3423H}/H9012\\H9016\\",
                "wordIndex": 8,
                "lex": {
                  "code": "H3423",
                  "lemma": "יָרַשׁ",
                  "translit": "ya.rash",
                  "morph": "H:V",
                  "gloss": "to possess: poor : poor/conquered<br>1) to seize, dispossess, take possession off, inherit, disinherit, occupy, impoverish, be an heir<br>1a) (Qal)<br>1a1) to take possession of<br>1a2) to inherit<br>1a3) to impoverish, come to poverty, be poor<br>1b) (Niphal) to be dispossessed, be impoverished, come to poverty<br>1c) (Piel) to devour<br>1d) (Hiphil)<br>1d1) to cause to possess or inherit<br>1d2) to cause others to possess or inherit<br>1d3) to impoverish<br>1d4) to dispossess<br>1d5) to destroy, bring to ruin, disinherit",
                  "raw": "H3423\tH3423I = a Meaning of\tH3423G\tיָרַשׁ\tya.rash\tH:V\tto possess: poor\t: poor/conquered<br>1) to seize, dispossess, take possession off, inherit, disinherit, occupy, impoverish, be an heir<br>1a) (Qal)<br>1a1) to take possession of<br>1a2) to inherit<br>1a3) to impoverish, come to poverty, be poor<br>1b) (Niphal) to be dispossessed, be impoverished, come to poverty<br>1c) (Piel) to devour<br>1d) (Hiphil)<br>1d1) to cause to possess or inherit<br>1d2) to cause others to possess or inherit<br>1d3) to impoverish<br>1d4) to dispossess<br>1d5) to destroy, bring to ruin, disinherit"
                }
              },
              {
                "text": "\\H9018",
                "wordIndex": 9,
                "lex": {
                  "code": "H9018",
                  "lemma": "ס",
                  "translit": "S",
                  "morph": "Punct.",
                  "gloss": "[¶] Punctuation Sameq paragraph: ends a lectionary section",
                  "raw": "H9018\tH9018 =\tH9018\tס\tS\tPunct.\t[¶]\tPunctuation Sameq paragraph: ends a lectionary section"
                }
              },
              {
                "text": "HVqv2ms/Sh",
                "wordIndex": 10
              },
              {
                "text": "H3423H",
                "wordIndex": 11,
                "lex": {
                  "code": "H3423",
                  "lemma": "יָרַשׁ",
                  "translit": "ya.rash",
                  "morph": "H:V",
                  "gloss": "to possess: poor : poor/conquered<br>1) to seize, dispossess, take possession off, inherit, disinherit, occupy, impoverish, be an heir<br>1a) (Qal)<br>1a1) to take possession of<br>1a2) to inherit<br>1a3) to impoverish, come to poverty, be poor<br>1b) (Niphal) to be dispossessed, be impoverished, come to poverty<br>1c) (Piel) to devour<br>1d) (Hiphil)<br>1d1) to cause to possess or inherit<br>1d2) to cause others to possess or inherit<br>1d3) to impoverish<br>1d4) to dispossess<br>1d5) to destroy, bring to ruin, disinherit",
                  "raw": "H3423\tH3423I = a Meaning of\tH3423G\tיָרַשׁ\tya.rash\tH:V\tto possess: poor\t: poor/conquered<br>1) to seize, dispossess, take possession off, inherit, disinherit, occupy, impoverish, be an heir<br>1a) (Qal)<br>1a1) to take possession of<br>1a2) to inherit<br>1a3) to impoverish, come to poverty, be poor<br>1b) (Niphal) to be dispossessed, be impoverished, come to poverty<br>1c) (Piel) to devour<br>1d) (Hiphil)<br>1d1) to cause to possess or inherit<br>1d2) to cause others to possess or inherit<br>1d3) to impoverish<br>1d4) to dispossess<br>1d5) to destroy, bring to ruin, disinherit"
                }
              },
              {
                "text": "{H3423H=יָרַשׁ=:",
                "wordIndex": 12,
                "lex": {
                  "code": "H3423",
                  "lemma": "יָרַשׁ",
                  "translit": "ya.rash",
                  "morph": "H:V",
                  "gloss": "to possess: poor : poor/conquered<br>1) to seize, dispossess, take possession off, inherit, disinherit, occupy, impoverish, be an heir<br>1a) (Qal)<br>1a1) to take possession of<br>1a2) to inherit<br>1a3) to impoverish, come to poverty, be poor<br>1b) (Niphal) to be dispossessed, be impoverished, come to poverty<br>1c) (Piel) to devour<br>1d) (Hiphil)<br>1d1) to cause to possess or inherit<br>1d2) to cause others to possess or inherit<br>1d3) to impoverish<br>1d4) to dispossess<br>1d5) to destroy, bring to ruin, disinherit",
                  "raw": "H3423\tH3423I = a Meaning of\tH3423G\tיָרַשׁ\tya.rash\tH:V\tto possess: poor\t: poor/conquered<br>1) to seize, dispossess, take possession off, inherit, disinherit, occupy, impoverish, be an heir<br>1a) (Qal)<br>1a1) to take possession of<br>1a2) to inherit<br>1a3) to impoverish, come to poverty, be poor<br>1b) (Niphal) to be dispossessed, be impoverished, come to poverty<br>1c) (Piel) to devour<br>1d) (Hiphil)<br>1d1) to cause to possess or inherit<br>1d2) to cause others to possess or inherit<br>1d3) to impoverish<br>1d4) to dispossess<br>1d5) to destroy, bring to ruin, disinherit"
                }
              },
              {
                "text": "take»to",
                "wordIndex": 13
              },
              {
                "text": "possess:2_take;_conquer;_drive_out}/H9012=ה=emph.\\H9016=׃=verseEnd\\",
                "wordIndex": 14,
                "lex": {
                  "code": "H9012",
                  "lemma": "ה/",
                  "translit": "h",
                  "morph": "Suffix",
                  "gloss": "[emph.?] Suffix  hé – paragogic: adds emphasis",
                  "raw": "H9012\tH9012 =\tH9012\tה/\th\tSuffix\t[emph.?]\tSuffix  hé – paragogic: adds emphasis"
                }
              },
              {
                "text": "\\H9018=ס=section",
                "wordIndex": 15,
                "lex": {
                  "code": "H9018",
                  "lemma": "ס",
                  "translit": "S",
                  "morph": "Punct.",
                  "gloss": "[¶] Punctuation Sameq paragraph: ends a lectionary section",
                  "raw": "H9018\tH9018 =\tH9018\tס\tS\tPunct.\t[¶]\tPunctuation Sameq paragraph: ends a lectionary section"
                }
              }
            ],
            "originalVerseText": "#11=L יְרָֽשָׁ/ה\\׃\\ \\ס ye.Ra.sha/h take possession of/ ! {H3423H}/H9012\\H9016\\ \\H9018 HVqv2ms/Sh H3423H {H3423H=יָרַשׁ=: take»to possess:2_take;_conquer;_drive_out}/H9012=ה=emph.\\H9016=׃=verseEnd\\ \\H9018=ס=section"
          }
        },
        {
          "chapter": 33,
          "verse": 24,
          "text": "Here’s what Moses said about Asher.\n“Asher is the most blessed of sons.\nLet his brothers show favor to him.\nLet him wash his feet with olive oil.",
          "isHeading": false,
          "interlinear": {
            "tokens": [
              {
                "text": "#11=L",
                "wordIndex": 0
              },
              {
                "text": "רַגְלֽ/וֹ\\׃",
                "wordIndex": 1
              },
              {
                "text": "rag.L/o",
                "wordIndex": 2
              },
              {
                "text": "foot/",
                "wordIndex": 3
              },
              {
                "text": "his",
                "wordIndex": 4
              },
              {
                "text": "{H7272}/H9023\\H9016",
                "wordIndex": 5,
                "lex": {
                  "code": "H7272",
                  "lemma": "רֶ֫גֶל",
                  "translit": "re.gel",
                  "morph": "H:N-F",
                  "gloss": "foot 1) foot<br>1a) foot, leg<br>1b) of God (anthropomorphic)<br>1c) of seraphim, cherubim, idols, animals, table<br>1d) according to the pace of (with prep)<br>1e) three times (feet, paces)<BR>Aramaic equivalent: <i>re.gal</i> (רְגַל \"foot\" H7271)",
                  "raw": "H7272\tH7272 =\tH7272\tרֶ֫גֶל\tre.gel\tH:N-F\tfoot\t1) foot<br>1a) foot, leg<br>1b) of God (anthropomorphic)<br>1c) of seraphim, cherubim, idols, animals, table<br>1d) according to the pace of (with prep)<br>1e) three times (feet, paces)<BR>Aramaic equivalent: <i>re.gal</i> (רְגַל \"foot\" H7271)"
                }
              },
              {
                "text": "HNcfsc/Sp3ms",
                "wordIndex": 6
              },
              {
                "text": "H7272",
                "wordIndex": 7,
                "lex": {
                  "code": "H7272",
                  "lemma": "רֶ֫גֶל",
                  "translit": "re.gel",
                  "morph": "H:N-F",
                  "gloss": "foot 1) foot<br>1a) foot, leg<br>1b) of God (anthropomorphic)<br>1c) of seraphim, cherubim, idols, animals, table<br>1d) according to the pace of (with prep)<br>1e) three times (feet, paces)<BR>Aramaic equivalent: <i>re.gal</i> (רְגַל \"foot\" H7271)",
                  "raw": "H7272\tH7272 =\tH7272\tרֶ֫גֶל\tre.gel\tH:N-F\tfoot\t1) foot<br>1a) foot, leg<br>1b) of God (anthropomorphic)<br>1c) of seraphim, cherubim, idols, animals, table<br>1d) according to the pace of (with prep)<br>1e) three times (feet, paces)<BR>Aramaic equivalent: <i>re.gal</i> (רְגַל \"foot\" H7271)"
                }
              },
              {
                "text": "{H7272=רֶ֫גֶל=foot}/H9023=Ps3m=his\\H9016=׃=verseEnd",
                "wordIndex": 8,
                "lex": {
                  "code": "H7272",
                  "lemma": "רֶ֫גֶל",
                  "translit": "re.gel",
                  "morph": "H:N-F",
                  "gloss": "foot 1) foot<br>1a) foot, leg<br>1b) of God (anthropomorphic)<br>1c) of seraphim, cherubim, idols, animals, table<br>1d) according to the pace of (with prep)<br>1e) three times (feet, paces)<BR>Aramaic equivalent: <i>re.gal</i> (רְגַל \"foot\" H7271)",
                  "raw": "H7272\tH7272 =\tH7272\tרֶ֫גֶל\tre.gel\tH:N-F\tfoot\t1) foot<br>1a) foot, leg<br>1b) of God (anthropomorphic)<br>1c) of seraphim, cherubim, idols, animals, table<br>1d) according to the pace of (with prep)<br>1e) three times (feet, paces)<BR>Aramaic equivalent: <i>re.gal</i> (רְגַל \"foot\" H7271)"
                }
              }
            ],
            "originalVerseText": "#11=L רַגְלֽ/וֹ\\׃ rag.L/o foot/ his {H7272}/H9023\\H9016 HNcfsc/Sp3ms H7272 {H7272=רֶ֫גֶל=foot}/H9023=Ps3m=his\\H9016=׃=verseEnd"
          }
        },
        {
          "chapter": 33,
          "verse": 25,
          "text": "The bars of his gates will be made out of iron and bronze.\nHis strength will last as long as he lives.",
          "isHeading": false,
          "interlinear": {
            "tokens": [
              {
                "text": "#05=L",
                "wordIndex": 0
              },
              {
                "text": "דָּבְאֶֽ/ךָ\\׃",
                "wordIndex": 1
              },
              {
                "text": "da.ve.'E./kha",
                "wordIndex": 2
              },
              {
                "text": "strength/",
                "wordIndex": 3
              },
              {
                "text": "your",
                "wordIndex": 4
              },
              {
                "text": "{H1679}/H9021\\H9016",
                "wordIndex": 5,
                "lex": {
                  "code": "H1679",
                  "lemma": "דֹּ֫בֶא",
                  "translit": "do.ve",
                  "morph": "H:N-M",
                  "gloss": "strength strength?, rest? (meaning obscure)",
                  "raw": "H1679\tH1679 =\tH1679\tדֹּ֫בֶא\tdo.ve\tH:N-M\tstrength\tstrength?, rest? (meaning obscure)"
                }
              },
              {
                "text": "HNcmsc/Sp2ms",
                "wordIndex": 6
              },
              {
                "text": "H1679",
                "wordIndex": 7,
                "lex": {
                  "code": "H1679",
                  "lemma": "דֹּ֫בֶא",
                  "translit": "do.ve",
                  "morph": "H:N-M",
                  "gloss": "strength strength?, rest? (meaning obscure)",
                  "raw": "H1679\tH1679 =\tH1679\tדֹּ֫בֶא\tdo.ve\tH:N-M\tstrength\tstrength?, rest? (meaning obscure)"
                }
              },
              {
                "text": "{H1679=דֹּ֫בֶא=rest}/H9021=Ps2m=your\\H9016=׃=verseEnd",
                "wordIndex": 8,
                "lex": {
                  "code": "H1679",
                  "lemma": "דֹּ֫בֶא",
                  "translit": "do.ve",
                  "morph": "H:N-M",
                  "gloss": "strength strength?, rest? (meaning obscure)",
                  "raw": "H1679\tH1679 =\tH1679\tדֹּ֫בֶא\tdo.ve\tH:N-M\tstrength\tstrength?, rest? (meaning obscure)"
                }
              }
            ],
            "originalVerseText": "#05=L דָּבְאֶֽ/ךָ\\׃ da.ve.'E./kha strength/ your {H1679}/H9021\\H9016 HNcmsc/Sp2ms H1679 {H1679=דֹּ֫בֶא=rest}/H9021=Ps2m=your\\H9016=׃=verseEnd"
          }
        },
        {
          "chapter": 33,
          "verse": 26,
          "text": "He rides in the heavens to help you.\nHe rides on the clouds in his glory.",
          "isHeading": false,
          "interlinear": {
            "tokens": [
              {
                "text": "#08=L",
                "wordIndex": 0
              },
              {
                "text": "שְׁחָקִֽים\\׃",
                "wordIndex": 1
              },
              {
                "text": "she.cha.Kim",
                "wordIndex": 2
              },
              {
                "text": "clouds",
                "wordIndex": 3
              },
              {
                "text": "{H7834}\\H9016",
                "wordIndex": 4,
                "lex": {
                  "code": "H7834",
                  "lemma": "שַׁ֫חַק",
                  "translit": "sha.chaq",
                  "morph": "H:N-M",
                  "gloss": "cloud 1) dust, cloud<br>1a) fine dust<br>1b) (thin) cloud",
                  "raw": "H7834\tH7834 =\tH7834\tשַׁ֫חַק\tsha.chaq\tH:N-M\tcloud\t1) dust, cloud<br>1a) fine dust<br>1b) (thin) cloud"
                }
              },
              {
                "text": "HNcmpa",
                "wordIndex": 5
              },
              {
                "text": "H7834",
                "wordIndex": 6,
                "lex": {
                  "code": "H7834",
                  "lemma": "שַׁ֫חַק",
                  "translit": "sha.chaq",
                  "morph": "H:N-M",
                  "gloss": "cloud 1) dust, cloud<br>1a) fine dust<br>1b) (thin) cloud",
                  "raw": "H7834\tH7834 =\tH7834\tשַׁ֫חַק\tsha.chaq\tH:N-M\tcloud\t1) dust, cloud<br>1a) fine dust<br>1b) (thin) cloud"
                }
              },
              {
                "text": "{H7834=שַׁ֫חַק=cloud}\\H9016=׃=verseEnd",
                "wordIndex": 7,
                "lex": {
                  "code": "H7834",
                  "lemma": "שַׁ֫חַק",
                  "translit": "sha.chaq",
                  "morph": "H:N-M",
                  "gloss": "cloud 1) dust, cloud<br>1a) fine dust<br>1b) (thin) cloud",
                  "raw": "H7834\tH7834 =\tH7834\tשַׁ֫חַק\tsha.chaq\tH:N-M\tcloud\t1) dust, cloud<br>1a) fine dust<br>1b) (thin) cloud"
                }
              }
            ],
            "originalVerseText": "#08=L שְׁחָקִֽים\\׃ she.cha.Kim clouds {H7834}\\H9016 HNcmpa H7834 {H7834=שַׁ֫חַק=cloud}\\H9016=׃=verseEnd"
          }
        }
      ]
    }
  },
  "gospel": {
    "passage": "Acts 28:11 - 28:16",
    "versions": {
      "leb": [
        {
          "chapter": 28,
          "verse": 11,
          "text": "Now after three months we put out to sea in a ship that had wintered at the island, an Alexandrian one with the twin gods Castor and Pollux as its insignia.",
          "isHeading": false
        },
        {
          "chapter": 28,
          "verse": 12,
          "text": "And putting in at Syracuse, we stayed there three days.",
          "isHeading": false
        },
        {
          "chapter": 28,
          "verse": 13,
          "text": "From there we got underway and arrived at Rhegium, and after one day a south wind came up and on the second day we came to Puteoli,",
          "isHeading": false
        },
        {
          "chapter": 28,
          "verse": 14,
          "text": "where we found brothers, and were implored to stay with them seven days. And in this way we came to Rome.",
          "isHeading": false
        },
        {
          "chapter": 28,
          "verse": 15,
          "text": "And from there the brothers, when they heard the news about us, came to meet us as far as the Forum of Appius and Three Taverns. When he saw them, Paul gave thanks to God and took courage.",
          "isHeading": false
        },
        {
          "chapter": 28,
          "verse": 16,
          "text": "And when we entered into Rome, Paul was allowed to stay by himself with the soldier who was guarding him.",
          "isHeading": false
        }
      ],
      "nirv": [
        {
          "chapter": 28,
          "verse": 11,
          "text": "After three months we headed out to sea. We sailed in a ship that had stayed at the island during the winter. It was a ship from Alexandria. On the front of it the figures of twin gods were carved. Their names were Castor and Pollux.",
          "isHeading": false
        },
        {
          "chapter": 28,
          "verse": 12,
          "text": "We landed at Syracuse and stayed there for three days.",
          "isHeading": false
        },
        {
          "chapter": 28,
          "verse": 13,
          "text": "From there we sailed to Rhegium. The next day the south wind came up. The day after that, we reached Puteoli.",
          "isHeading": false
        },
        {
          "chapter": 28,
          "verse": 14,
          "text": "There we found some believers. They invited us to spend a week with them.\nAt last we came to Rome.",
          "isHeading": false
        },
        {
          "chapter": 28,
          "verse": 15,
          "text": "The brothers and sisters there had heard we were coming. They traveled as far as the Forum of Appius and the Three Taverns to meet us. When Paul saw these people, he thanked God and was cheered up.",
          "isHeading": false
        },
        {
          "chapter": 28,
          "verse": 16,
          "text": "When we got to Rome, Paul was allowed to live by himself. But a soldier guarded him.",
          "isHeading": false
        }
      ]
    }
  }
}